FULL_sub/FULL_sub.v
module FULL_sub(
	input a,b,c,
	output diff,bor
);
wire w1,w2,w3,w4,w5,w6;
xor(w1,a,b);
xor(diff,w1,c);
not(w2,a);
and(w3,w2,b);
and(w4,w2,c);
and(w5,b,c);
or(w6,w4,w5);
or(bor,w6,w3);
endmodule

FULL_sub/FULL_sub_tb.v
module FULL_sub_tb;
	reg a,b,c;
	wire diff,bor;
FULL_sub F1(
	.a(a),
	.b(b),
	.c(c),
	.diff(diff),
	.bor(bor)
);
initial begin
	$dumpfile("FULL_sub.vcd");
	$dumpvars(0,FULL_sub_tb);
$display("A B C | D B");
$monitor("%b %b %b  %b %b",a,b,c,diff,bor);
a=0;b=0;c=0;#10;
a=0;b=0;c=1;#10;
a=0;b=1;c=0;#10;
a=0;b=1;c=1;#10;
a=1;b=0;c=0;#10;
a=1;b=0;c=1;#10;
a=1;b=1;c=0;#10;
a=1;b=1;c=1;#10;
$finish;
end
endmodule;

FULL_sub/FULL_sub.vcd
$date
	Tue Jun 16 17:11:40 2026
$end
$version
	Icarus Verilog
$end
$timescale
	1s
$end
$scope module FULL_sub_tb $end
$var wire 1 ! diff $end
$var wire 1 " bor $end
$var reg 1 # a $end
$var reg 1 $ b $end
$var reg 1 % c $end
$scope module F1 $end
$var wire 1 # a $end
$var wire 1 $ b $end
$var wire 1 " bor $end
$var wire 1 % c $end
$var wire 1 ! diff $end
$var wire 1 & w1 $end
$var wire 1 ' w2 $end
$var wire 1 ( w3 $end
$var wire 1 ) w4 $end
$var wire 1 * w5 $end
$var wire 1 + w6 $end
$upscope $end
$upscope $end
$enddefinitions $end
$comment Show the parameter values. $end
$dumpall
$end
#0
$dumpvars
0+
0*
0)
0(
1'
0&
0%
0$
0#
0"
0!
$end
#10
1"
1+
1!
1)
1%
#20
0+
0)
1&
1(
0%
1$
#30
1+
0!
1)
1*
1%
#40
0"
0+
1!
0)
0(
0*
0'
0%
0$
1#
#50
0!
1%
#60
0&
0%
1$
#70
1"
1+
1!
1*
1%
