sequential/D_ff/D_ff.v
module d_ff(
    input clk,
    input d,
    input reset,
    output reg q
);

always @(posedge clk or posedge reset)
begin
    if (reset)
        q <= 1'b0;
    else
        q <= d;
end

endmodule

sequential/D_ff/D_ff_tb.v
module d_ff_tb;

    reg clk, d, reset;
    wire q;

    d_ff U1(
        .clk(clk),
        .d(d),
        .reset(reset),
        .q(q)
    );

    // Clock generation
    initial begin
        clk = 0;
        forever #5 clk = ~clk;
    end

    // Test stimulus
    initial begin
        $dumpfile("d_ff.vcd");
        $dumpvars(0, d_ff_tb);

        $display("Time\tReset\tClk\tD\tQ");
        $monitor("%0t\t%b\t%b\t%b\t%b", $time, reset, clk, d, q);

        // Apply reset
        reset = 1;
        d = 0;
        #10;
        reset = 0;
        d = 1; #10;
        d = 0; #10;
        d = 1; #10;
        d = 0; #10;
        reset = 1; #10;
        reset = 0;
        d = 1; #10;
        d = 0; #10;

        $finish;
    end

endmodule

sequential/D_ff/d_ff.vcd
$date
	Wed Jul  8 17:48:36 2026
$end
$version
	Icarus Verilog
$end
$timescale
	1s
$end
$scope module d_ff_tb $end
$var wire 1 ! q $end
$var reg 1 " clk $end
$var reg 1 # d $end
$var reg 1 $ reset $end
$scope module U1 $end
$var wire 1 " clk $end
$var wire 1 # d $end
$var wire 1 $ reset $end
$var reg 1 ! q $end
$upscope $end
$upscope $end
$enddefinitions $end
$comment Show the parameter values. $end
$dumpall
$end
#0
$dumpvars
1$
0#
0"
0!
$end
#5
1"
#10
0"
1#
0$
#15
1!
1"
#20
0"
0#
#25
0!
1"
#30
0"
1#
#35
1!
1"
#40
0"
0#
#45
0!
1"
#50
0"
1$
#55
1"
#60
0"
1#
0$
#65
1!
1"
#70
0"
0#
#75
0!
1"
