FULL_adder/FULL_adder.v
module FULL_adder(
	input a,b,c,
	output sum,carry
);
assign sum = a^b^c;
assign carry = ( ( a & b ) | ( a & c) | (b & c) );
endmodule

FULL_adder/FULL_adder_tb.v
module FULL_adder_tb;
	reg a,b,c;
	wire sum,carry;
FULL_adder F1(
	.a(a),
	.b(b),
	.c(c),
	.sum(sum),
	.carry(carry)
);
initial begin
	$dumpfile("FULL_adder.vcd");
	$dumpvars(0,FULL_adder_tb);
$display("A B C | S C");
$monitor("%b %b %b  %b %b",a,b,c,sum,carry);
a=0;b=0;c=0;#10;
a=0;b=0;c=1;#10;
a=0;b=1;c=0;#10;
a=0;b=1;c=1;#10;
a=1;b=0;c=0;#10;
a=1;b=0;c=1;#10;
a=1;b=1;c=0;#10;
a=1;b=1;c=1;#10;
$finish;
end
endmodule;

FULL_adder/FULL_adder.vcd
$date
	Wed Jun 10 20:32:02 2026
$end
$version
	Icarus Verilog
$end
$timescale
	1s
$end
$scope module FULL_adder_tb $end
$var wire 1 ! sum $end
$var wire 1 " carry $end
$var reg 1 # a $end
$var reg 1 $ b $end
$var reg 1 % c $end
$scope module F1 $end
$var wire 1 # a $end
$var wire 1 $ b $end
$var wire 1 % c $end
$var wire 1 " carry $end
$var wire 1 ! sum $end
$upscope $end
$upscope $end
$enddefinitions $end
$comment Show the parameter values. $end
$dumpall
$end
#0
$dumpvars
0%
0$
0#
0"
0!
$end
#10
1!
1%
#20
0%
1$
#30
1"
0!
1%
#40
0"
1!
0%
0$
1#
#50
1"
0!
1%
#60
0%
1$
#70
1!
1%
