FULL_adder_struct/OR_gate.v
module OR_gate(
	input a,
	input b,
	output y
);
 assign y = a | b;
endmodule;

HALF_Adder_struct/AND_gate.v
module AND_gate(
	input a,
	input b,
	output y
);
assign y = a & b;
endmodule

FULL_adder_struct/XOR_gate.v
module XOR_gate(
	input a,
	input b,
	output y
);
assign y = a ^ b;
endmodule

FULL_adder_struct/FULL_adder.v
module FULL_adder(
	input a,b,c,
	output sum,carry
);
wire w1,w2,w3,w4,w5;
XOR_gate G1(
	.a(a),
	.b(b),
	.y(w5)
);
XOR_gate G2(
	.a(w5),
	.b(c),
	.y(sum)
);
AND_gate G3(
	.a(a),
	.b(b),
	.y(w1)
);
AND_gate G4(
	.a(b),
	.b(c),
	.y(w2)
);
AND_gate G5(
	.a(a),
	.b(c),
	.y(w3)
);
OR_gate G6(
	.a(w1),
	.b(w2),
	.y(w4)
);
OR_gate G7(
	.a(w3),
	.b(w4),
	.y(carry)
);
endmodule

FULL_adder/FULL_adder_tb.v
module FULL_adder_tb;
	reg a,b,c;
	wire sum,carry;
FULL_adder F1(
	.a(a),
	.b(b),
	.c(c),
	.sum(sum),
	.carry(carry)
);
initial begin
	$dumpfile("FULL_adder.vcd");
	$dumpvars(0,FULL_adder_tb);
$display("A B C | S C");
$monitor("%b %b %b  %b %b",a,b,c,sum,carry);
a=0;b=0;c=0;#10;
a=0;b=0;c=1;#10;
a=0;b=1;c=0;#10;
a=0;b=1;c=1;#10;
a=1;b=0;c=0;#10;
a=1;b=0;c=1;#10;
a=1;b=1;c=0;#10;
a=1;b=1;c=1;#10;
$finish;
end
endmodule;

FULL_adder_struct/FULL_adder.vcd
$date
	Tue Jun 16 15:23:14 2026
$end
$version
	Icarus Verilog
$end
$timescale
	1s
$end
$scope module FULL_adder_tb $end
$var wire 1 ! sum $end
$var wire 1 " carry $end
$var reg 1 # a $end
$var reg 1 $ b $end
$var reg 1 % c $end
$scope module F1 $end
$var wire 1 # a $end
$var wire 1 $ b $end
$var wire 1 % c $end
$var wire 1 & w5 $end
$var wire 1 ' w4 $end
$var wire 1 ( w3 $end
$var wire 1 ) w2 $end
$var wire 1 * w1 $end
$var wire 1 ! sum $end
$var wire 1 " carry $end
$scope module G1 $end
$var wire 1 # a $end
$var wire 1 $ b $end
$var wire 1 & y $end
$upscope $end
$scope module G2 $end
$var wire 1 & a $end
$var wire 1 % b $end
$var wire 1 ! y $end
$upscope $end
$scope module G3 $end
$var wire 1 # a $end
$var wire 1 $ b $end
$var wire 1 * y $end
$upscope $end
$scope module G4 $end
$var wire 1 $ a $end
$var wire 1 % b $end
$var wire 1 ) y $end
$upscope $end
$scope module G5 $end
$var wire 1 # a $end
$var wire 1 % b $end
$var wire 1 ( y $end
$upscope $end
$scope module G6 $end
$var wire 1 * a $end
$var wire 1 ) b $end
$var wire 1 ' y $end
$upscope $end
$scope module G7 $end
$var wire 1 ( a $end
$var wire 1 ' b $end
$var wire 1 " y $end
$upscope $end
$upscope $end
$upscope $end
$enddefinitions $end
$comment Show the parameter values. $end
$dumpall
$end
#0
$dumpvars
0*
0)
0(
0'
0&
0%
0$
0#
0"
0!
$end
#10
1!
1%
#20
1&
0%
1$
#30
1"
1'
0!
1)
1%
#40
0"
0'
1!
0)
0%
0$
1#
#50
1"
0!
1(
1%
#60
1'
0(
0&
1*
0%
1$
#70
1!
1)
1(
1%
